Metadata-Version: 1.1
Name: django-twilio-sms-2
Version: 1.0.2
Summary: Twilio integration for SMS-based Django apps
Home-page: https://github.com/theskumar/django-twilio-sms-2
Author: Saurabh Kumar
Author-email: me@saurabh-kumar.com
License: MIT
Download-URL: https://github.com/theskumar/django-twilio-sms-2/zipball/master
Platform: UNKNOWN
Classifier: Development Status :: 4 - Beta
Classifier: Environment :: Web Environment
Classifier: Framework :: Django
Classifier: Intended Audience :: Developers
Classifier: License :: OSI Approved :: MIT License
Classifier: Operating System :: OS Independent
Classifier: Programming Language :: Python
Classifier: Programming Language :: Python :: 2.6
Classifier: Programming Language :: Python :: 2.7
Classifier: Programming Language :: Python :: 3.2
Classifier: Programming Language :: Python :: 3.3
Classifier: Topic :: Software Development :: Libraries :: Python Modules
